gammarers/aws_daily_cost_usage_report-stack/__init__.py
gammarers/aws_daily_cost_usage_report-stack/py.typed
gammarers/aws_daily_cost_usage_report-stack/_jsii/__init__.py
gammarers/aws_daily_cost_usage_report-stack/_jsii/aws-daily-cost-usage-report-stack@2.0.37.jsii.tgz
gammarers_aws_daily_cost_usage_report_stack-2.0.37.dist-info/LICENSE
gammarers_aws_daily_cost_usage_report_stack-2.0.37.dist-info/METADATA
gammarers_aws_daily_cost_usage_report_stack-2.0.37.dist-info/WHEEL
gammarers_aws_daily_cost_usage_report_stack-2.0.37.dist-info/top_level.txt
gammarers_aws_daily_cost_usage_report_stack-2.0.37.dist-info/RECORD
